<annotation>
	<folder>train</folder>
	<filename>map_739.jpg</filename>
	<path>D:\Data_map\Thư mục mới\train\map_739.jpg</path>
	<source>
		<database>Unknown</database>
	</source>
	<size>
		<width>486</width>
		<height>609</height>
		<depth>3</depth>
	</size>
	<segmented>0</segmented>
	<object>
		<name>Island</name>
		<pose>Unspecified</pose>
		<truncated>0</truncated>
		<difficult>0</difficult>
		<bndbox>
			<xmin>249</xmin>
			<ymin>340</ymin>
			<xmax>317</xmax>
			<ymax>377</ymax>
		</bndbox>
	</object>
</annotation>
