<annotation>
	<folder>train</folder>
	<filename>map_1695.jpg</filename>
	<path>D:\Data_map\Thư mục mới\train\map_1695.jpg</path>
	<source>
		<database>Unknown</database>
	</source>
	<size>
		<width>698</width>
		<height>964</height>
		<depth>3</depth>
	</size>
	<segmented>0</segmented>
	<object>
		<name>Island</name>
		<pose>Unspecified</pose>
		<truncated>0</truncated>
		<difficult>0</difficult>
		<bndbox>
			<xmin>527</xmin>
			<ymin>392</ymin>
			<xmax>668</xmax>
			<ymax>524</ymax>
		</bndbox>
	</object>
	<object>
		<name>Island</name>
		<pose>Unspecified</pose>
		<truncated>0</truncated>
		<difficult>0</difficult>
		<bndbox>
			<xmin>519</xmin>
			<ymin>869</ymin>
			<xmax>654</xmax>
			<ymax>954</ymax>
		</bndbox>
	</object>
</annotation>
