<annotation>
	<folder>train</folder>
	<filename>map_1209.jpg</filename>
	<path>D:\Data_map\Thư mục mới\train\map_1209.jpg</path>
	<source>
		<database>Unknown</database>
	</source>
	<size>
		<width>724</width>
		<height>1024</height>
		<depth>3</depth>
	</size>
	<segmented>0</segmented>
	<object>
		<name>Island</name>
		<pose>Unspecified</pose>
		<truncated>0</truncated>
		<difficult>0</difficult>
		<bndbox>
			<xmin>405</xmin>
			<ymin>380</ymin>
			<xmax>519</xmax>
			<ymax>478</ymax>
		</bndbox>
	</object>
	<object>
		<name>Island</name>
		<pose>Unspecified</pose>
		<truncated>0</truncated>
		<difficult>0</difficult>
		<bndbox>
			<xmin>446</xmin>
			<ymin>649</ymin>
			<xmax>655</xmax>
			<ymax>811</ymax>
		</bndbox>
	</object>
</annotation>
